README.md
setup.py
kms_encrypter/__init__.py
kms_encrypter.egg-info/PKG-INFO
kms_encrypter.egg-info/SOURCES.txt
kms_encrypter.egg-info/dependency_links.txt
kms_encrypter.egg-info/not-zip-safe
kms_encrypter.egg-info/requires.txt
kms_encrypter.egg-info/top_level.txt